Metadata-Version: 2.1
Name: mddtoolkit
Version: 0.3.0
Summary: A package for modelling diffusion processes.
Classifier: Programming Language :: Python :: 3
Classifier: License :: OSI Approved :: MIT License
Classifier: Operating System :: OS Independent
Requires-Python: >=3.9
Requires-Dist: numpy
Requires-Dist: torch
Requires-Dist: scipy
Requires-Dist: pandas
Requires-Dist: matplotlib
Requires-Dist: pyyaml
Requires-Dist: pathos
Requires-Dist: pytest
Requires-Dist: tabulate
